{
  "title": "菜根谭摘录",
  "englishTitle": "Vegetable Root Sayings",
  "description": "明朝洪应明所著《菜根谭》是中国传统文化中的处世哲学经典，包含了丰富的修身养性、为人处世的智慧箴言。",
  "quotes": [
    {
      "id": 1,
      "quote": "宠辱不惊，闲看庭前花开花落；去留无意，漫随天外云卷云舒。",
      "source": "《菜根谭·闲适篇》",
      "fullText": "宠辱不惊，闲看庭前花开花落；去留无意，漫随天外云卷云舒。人当超然物外，不为外物所累，心自安闲。",
      "category": "心境"
    },
    {
      "id": 2,
      "quote": "处世让一步为高，退步即进步的张本；待人宽一分是福，利人实利己的根基。",
      "source": "《菜根谭·处世篇》",
      "fullText": "处世让一步为高，退步即进步的张本；待人宽一分是福，利人实利己的根基。凡事退一步，天地自然宽；待人宽一分，福气自然来。",
      "category": "处世"
    },
    {
      "id": 3,
      "quote": "天地有万古，此身不再得；人生只百年，此日最易过。",
      "source": "《菜根谭·惜时篇》",
      "fullText": "天地有万古，此身不再得；人生只百年，此日最易过。幸生其间者，不可不知有生之乐，亦不可不怀虚生之忧。",
      "category": "惜时"
    },
    {
      "id": 4,
      "quote": "为善不见其益，如草里冬瓜自应暗长；为恶不见其损，如庭前春雪，当必潜消。",
      "source": "《菜根谭·因果篇》",
      "fullText": "为善不见其益，如草里冬瓜自应暗长；为恶不见其损，如庭前春雪，当必潜消。善恶之报，如影随形，虽迟必至。",
      "category": "因果"
    },
    {
      "id": 5,
      "quote": "心体光明，暗室中有青天；念头暗昧，白日下有厉鬼。",
      "source": "《菜根谭·心性篇》",
      "fullText": "心体光明，暗室中有青天；念头暗昧，白日下有厉鬼。故君子之心，常存敬畏，虽处暗室，亦如对神明。",
      "category": "心性"
    },
    {
      "id": 6,
      "quote": "居逆境中，周身皆针砭药石，砥节砺行而不觉；处顺境中，眼前尽兵刃戈矛，销膏靡骨而不知。",
      "source": "《菜根谭·顺逆篇》",
      "fullText": "居逆境中，周身皆针砭药石，砥节砺行而不觉；处顺境中，眼前尽兵刃戈矛，销膏靡骨而不知。故君子处逆境则加勉，处顺境则加敬。",
      "category": "顺逆"
    },
    {
      "id": 7,
      "quote": "交友须带三分侠气，做人要存一点素心。",
      "source": "《菜根谭·交友篇》",
      "fullText": "交友须带三分侠气，做人要存一点素心。侠气者，慷慨仗义；素心者，纯朴真诚。如此方能长久。",
      "category": "交友"
    },
    {
      "id": 8,
      "quote": "风来疏竹，风过而竹不留声；雁渡寒潭，雁去而潭不留影。",
      "source": "《菜根谭·心境篇》",
      "fullText": "风来疏竹，风过而竹不留声；雁渡寒潭，雁去而潭不留影。故君子事来而心始现，事去而心随空。",
      "category": "心境"
    },
    {
      "id": 9,
      "quote": "径路窄处，留一步与人行；滋味浓时，减三分让人尝。",
      "source": "《菜根谭·谦让篇》",
      "fullText": "径路窄处，留一步与人行；滋味浓时，减三分让人尝。此是涉世一极安乐法，亦是处世一极受用法。",
      "category": "谦让"
    },
    {
      "id": 10,
      "quote": "天地寂然不动，而气机无息稍停；日月尽夜奔驰，而贞明万古不易。",
      "source": "《菜根谭·天道篇》",
      "fullText": "天地寂然不动，而气机无息稍停；日月尽夜奔驰，而贞明万古不易。故君子闲时要有吃紧的心思，忙处要有悠闲的趣味。",
      "category": "天道"
    },
    {
      "id": 11,
      "quote": "君子之心，雨过天晴；小人之心，鼠目寸光。",
      "source": "《菜根谭·君子篇》",
      "fullText": "君子之心，雨过天晴；小人之心，鼠目寸光。故君子坦荡荡，小人长戚戚。",
      "category": "君子"
    },
    {
      "id": 12,
      "quote": "欲做精金美玉的人品，定从烈火中锻来；思立掀天揭地的事功，须向薄冰上履过。",
      "source": "《菜根谭·修身篇》",
      "fullText": "欲做精金美玉的人品，定从烈火中锻来；思立掀天揭地的事功，须向薄冰上履过。不经一番寒彻骨，怎得梅花扑鼻香。",
      "category": "修身"
    },
    {
      "id": 13,
      "quote": "立身不高一步立，如尘里振衣，泥中濯足，如何超达？",
      "source": "《菜根谭·立志篇》",
      "fullText": "立身不高一步立，如尘里振衣，泥中濯足，如何超达？处世不退一步处，如飞蛾投烛，羝羊触藩，如何安乐？",
      "category": "立志"
    },
    {
      "id": 14,
      "quote": "学者要有段兢业的心思，又要有段潇洒的趣味。",
      "source": "《菜根谭·治学篇》",
      "fullText": "学者要有段兢业的心思，又要有段潇洒的趣味。若一味敛束清苦，是有秋杀无春生，何以发育万物？",
      "category": "治学"
    },
    {
      "id": 15,
      "quote": "面前的田地要放得宽，使人无不平之叹；身后的惠泽要流得久，使人有不匮之思。",
      "source": "《菜根谭·仁德篇》",
      "fullText": "面前的田地要放得宽，使人无不平之叹；身后的惠泽要流得久，使人有不匮之思。如此方可谓达人也。",
      "category": "仁德"
    },
    {
      "id": 16,
      "quote": "耳中常闻逆耳之言，心中常有拂心之事，才是进德修行的砥石。",
      "source": "《菜根谭·修身篇》",
      "fullText": "耳中常闻逆耳之言，心中常有拂心之事，才是进德修行的砥石。若言言悦耳，事事快心，便把此生理在鸩毒中矣。",
      "category": "修身"
    },
    {
      "id": 17,
      "quote": "文章做到极处，无有他奇，只是恰好；人品做到极处，无有他异，只是本然。",
      "source": "《菜根谭·人品篇》",
      "fullText": "文章做到极处，无有他奇，只是恰好；人品做到极处，无有他异，只是本然。能守住本然之心，便是至善之境。",
      "category": "人品"
    },
    {
      "id": 18,
      "quote": "处世不必邀功，无过便是功；与人不求感德，无怨便是德。",
      "source": "《菜根谭·处世篇》",
      "fullText": "处世不必邀功，无过便是功；与人不求感德，无怨便是德。此真乃处世之大道也。",
      "category": "处世"
    },
    {
      "id": 19,
      "quote": "攻人之恶勿太严，要思其堪受；教人以善勿过高，当使其可从。",
      "source": "《菜根谭·教化篇》",
      "fullText": "攻人之恶勿太严，要思其堪受；教人以善勿过高，当使其可从。教化之道，贵在循序渐进。",
      "category": "教化"
    },
    {
      "id": 20,
      "quote": "富贵家宜宽厚，而反忌刻，是富贵而贫贱其行矣！如何能享？",
      "source": "《菜根谭·富贵篇》",
      "fullText": "富贵家宜宽厚，而反忌刻，是富贵而贫贱其行矣！如何能享？聪明人宜敛藏，而反炫耀，是聪明而愚懵其病矣！如何不败？",
      "category": "富贵"
    },
    {
      "id": 21,
      "quote": "人情反覆，世路崎岖。行不去处，须知退一步之法；行得去处，务加让三分之功。",
      "source": "《菜根谭·处世篇》",
      "fullText": "人情反覆，世路崎岖。行不去处，须知退一步之法；行得去处，务加让三分之功。退一步海阔天空，让三分心平气和。",
      "category": "处世"
    },
    {
      "id": 22,
      "quote": "君子处患难而不忧，当宴游而惕虑；遇权豪而不惧，对茕独而惊心。",
      "source": "《菜根谭·君子篇》",
      "fullText": "君子处患难而不忧，当宴游而惕虑；遇权豪而不惧，对茕独而惊心。此乃君子之常德也。",
      "category": "君子"
    },
    {
      "id": 23,
      "quote": "肝受病则目不能视，肾受病则耳不能听；受病于人所不见，必发于人所共见。",
      "source": "《菜根谭·养生篇》",
      "fullText": "肝受病则目不能视，肾受病则耳不能听；受病于人所不见，必发于人所共见。故君子欲无得罪于昭昭，先无得罪于冥冥。",
      "category": "养生"
    },
    {
      "id": 24,
      "quote": "家庭有个真佛，日用有种真道。人能诚心和气、愉色婉言，使父母兄弟间形骸两释、意气交流，胜于调息观心万倍矣！",
      "source": "《菜根谭·家庭篇》",
      "fullText": "家庭有个真佛，日用有种真道。人能诚心和气、愉色婉言，使父母兄弟间形骸两释、意气交流，胜于调息观心万倍矣！",
      "category": "家庭"
    },
    {
      "id": 25,
      "quote": "磨砺当如百炼之金，急就者非邃养；施为欲试千钧之弩，轻发者无宏功。",
      "source": "《菜根谭·修养篇》",
      "fullText": "磨砺当如百炼之金，急就者非邃养；施为欲试千钧之弩，轻发者无宏功。厚积薄发，方能成大事。",
      "category": "修养"
    },
    {
      "id": 26,
      "quote": "居卑而后知登高之为危，处晦而后知向明之太霭；守静而后知好动之过劳，养默而后知多言之为躁。",
      "source": "《菜根谭·处世篇》",
      "fullText": "居卑而后知登高之为危，处晦而后知向明之太霭；守静而后知好动之过劳，养默而后知多言之为躁。世事皆有两面，不可不察。",
      "category": "处世"
    },
    {
      "id": 27,
      "quote": "放得功名富贵之心下，便可脱凡；放得道德仁义之心下，才可入圣。",
      "source": "《菜根谭·境界篇》",
      "fullText": "放得功名富贵之心下，便可脱凡；放得道德仁义之心下，才可入圣。放下执念，方能得大自在。",
      "category": "境界"
    },
    {
      "id": 28,
      "quote": "无事便思有闲杂念想否。有事便思有粗浮意气否。得意便思有骄矜辞色否。失意便思有怨望情怀否。",
      "source": "《菜根谭·自省篇》",
      "fullText": "无事便思有闲杂念想否。有事便思有粗浮意气否。得意便思有骄矜辞色否。失意便思有怨望情怀否。时时检点，才见真功夫。",
      "category": "自省"
    },
    {
      "id": 29,
      "quote": "醲肥辛甘非真味，真味只是淡；神奇卓异非至人，至人只是常。",
      "source": "《菜根谭·真味篇》",
      "fullText": "醲肥辛甘非真味，真味只是淡；神奇卓异非至人，至人只是常。平淡是真，常道最贵。",
      "category": "真味"
    },
    {
      "id": 30,
      "quote": "天地有万古，此身不再得；人生只百年，此日最易过。幸生其间者，不可不知有生之乐，亦不可不怀虚生之忧。",
      "source": "《菜根谭·惜时篇》",
      "fullText": "天地有万古，此身不再得；人生只百年，此日最易过。幸生其间者，不可不知有生之乐，亦不可不怀虚生之忧。",
      "category": "惜时"
    },
    {
      "id": 31,
      "quote": "君子之心，常存敬畏，虽处暗室，亦如对神明。",
      "source": "《菜根谭·敬畏篇》",
      "fullText": "君子之心，常存敬畏，虽处暗室，亦如对神明。暗室之中，常如有天；青天白日，常如有神。",
      "category": "敬畏"
    },
    {
      "id": 32,
      "quote": "降魔者先降自心，心伏则群魔退听；驭横者先驭此气，气平则外横不侵。",
      "source": "《菜根谭·心性篇》",
      "fullText": "降魔者先降自心，心伏则群魔退听；驭横者先驭此气，气平则外横不侵。故曰：心正则邪不侵，气平则横不扰。",
      "category": "心性"
    },
    {
      "id": 33,
      "quote": "持身不可太皎洁，一切污辱垢秽要茹纳得；处世不可太分明，一切贤愚好丑要包容得。",
      "source": "《菜根谭·容人篇》",
      "fullText": "持身不可太皎洁，一切污辱垢秽要茹纳得；处世不可太分明，一切贤愚好丑要包容得。君子之量，宜宏廓而不宜狭隘。",
      "category": "容人"
    },
    {
      "id": 34,
      "quote": "我有功于人不可念，而过则不可不念；人有恩于我不可忘，而怨则不可不忘。",
      "source": "《菜根谭·感恩篇》",
      "fullText": "我有功于人不可念，而过则不可不念；人有恩于我不可忘，而怨则不可不忘。君子以德报怨，小人以怨报德。",
      "category": "感恩"
    },
    {
      "id": 35,
      "quote": "恩宜自淡而浓，先浓后淡者人忘其惠；威宜自严而宽，先宽后严者人怨其酷。",
      "source": "《菜根谭·恩威篇》",
      "fullText": "恩宜自淡而浓，先浓后淡者人忘其惠；威宜自严而宽，先宽后严者人怨其酷。施恩宜渐，施威宜速。",
      "category": "恩威"
    },
    {
      "id": 36,
      "quote": "人之短处，要曲为弥缝，如暴而扬之，是以短攻短；人有顽固，要善为化海，如忿而疾之，是以顽济顽。",
      "source": "《菜根谭·教化篇》",
      "fullText": "人之短处，要曲为弥缝，如暴而扬之，是以短攻短；人有顽固，要善为化海，如忿而疾之，是以顽济顽。善教者如春风化雨，润物无声。",
      "category": "教化"
    },
    {
      "id": 37,
      "quote": "遇沉沉不语之士，且莫输心；见悻悻自好之人，应须防口。",
      "source": "《菜根谭·交际篇》",
      "fullText": "遇沉沉不语之士，且莫输心；见悻悻自好之人，应须防口。交友贵在知心，知人贵在知心。",
      "category": "交际"
    },
    {
      "id": 38,
      "quote": "觉人之诈不形于言，受人之侮不动于色，此中有无穷意味，亦有无穷受用。",
      "source": "《菜根谭·涵养篇》",
      "fullText": "觉人之诈不形于言，受人之侮不动于色，此中有无穷意味，亦有无穷受用。忍一时风平浪静，退一步海阔天空。",
      "category": "涵养"
    },
    {
      "id": 39,
      "quote": "淡泊之士，必为浓艳者所疑；检饰之人，多为放肆者所忌。",
      "source": "《菜根谭·处世篇》",
      "fullText": "淡泊之士，必为浓艳者所疑；检饰之人，多为放肆者所忌。君子处浊世，当独善其身。",
      "category": "处世"
    },
    {
      "id": 40,
      "quote": "爵位不宜太盛，太盛则危；能事不宜尽毕，尽毕则衰；行谊不宜过高，过高则谤兴而毁来。",
      "source": "《菜根谭·中庸篇》",
      "fullText": "爵位不宜太盛，太盛则危；能事不宜尽毕，尽毕则衰；行谊不宜过高，过高则谤兴而毁来。中庸之道，贵在适度。",
      "category": "中庸"
    },
    {
      "id": 41,
      "quote": "处世让一步为高，退步即进步的张本；待人宽一分是福，利人实利己的根基。",
      "source": "《菜根谭·处世篇》",
      "fullText": "处世让一步为高，退步即进步的张本；待人宽一分是福，利人实利己的根基。凡事退一步，天地自然宽；待人宽一分，福气自然来。",
      "category": "处世"
    },
    {
      "id": 42,
      "quote": "居盈满者，如水之将溢未溢，切忌再加一滴；处危急者，如木之将折未折，切忌再加一搦。",
      "source": "《菜根谭·警醒篇》",
      "fullText": "居盈满者，如水之将溢未溢，切忌再加一滴；处危急者，如木之将折未折，切忌再加一搦。物极必反，盛极必衰。",
      "category": "警醒"
    },
    {
      "id": 43,
      "quote": "冷眼观人，冷耳听语，冷情当感，冷心思理。",
      "source": "《菜根谭·冷静篇》",
      "fullText": "冷眼观人，冷耳听语，冷情当感，冷心思理。冷静客观，方能明辨是非。",
      "category": "冷静"
    },
    {
      "id": 44,
      "quote": "闻恶不可就恶，恐为谗夫泄怒；闻善不可急亲，恐引奸人进身。",
      "source": "《菜根谭·明辨篇》",
      "fullText": "闻恶不可就恶，恐为谗夫泄怒；闻善不可急亲，恐引奸人进身。兼听则明，偏信则暗。",
      "category": "明辨"
    },
    {
      "id": 45,
      "quote": "性躁心粗者一事无成，心和气平者百福自集。",
      "source": "《菜根谭·心平篇》",
      "fullText": "性躁心粗者一事无成，心和气平者百福自集。心平气和，万事皆顺。",
      "category": "心平"
    },
    {
      "id": 46,
      "quote": "用人不宜刻，刻则思效者去；交友不宜滥，滥则贡谀者来。",
      "source": "《菜根谭·用人篇》",
      "fullText": "用人不宜刻，刻则思效者去；交友不宜滥，滥则贡谀者来。用人贵在宽厚，交友贵在真诚。",
      "category": "用人"
    },
    {
      "id": 47,
      "quote": "风斜雨急处要立得脚定，花浓柳艳处要着得眼高，路危径险处要回得头早。",
      "source": "《菜根谭·定力篇》",
      "fullText": "风斜雨急处要立得脚定，花浓柳艳处要着得眼高，路危径险处要回得头早。君子之道，贵在坚持。",
      "category": "定力"
    },
    {
      "id": 48,
      "quote": "节义之人济以和衷，才不启忿争之路；功名之士承以谦德，方不开嫉妒之门。",
      "source": "《菜根谭·谦和篇》",
      "fullText": "节义之人济以和衷，才不启忿争之路；功名之士承以谦德，方不开嫉妒之门。谦受益，满招损。",
      "category": "谦和"
    },
    {
      "id": 49,
      "quote": "士大夫居官不可竿牍无节，要使人难见，以杜幸端；居乡不可崖岸太高，要使人易见，以致旧好。",
      "source": "《菜根谭·为官篇》",
      "fullText": "士大夫居官不可竿牍无节，要使人难见，以杜幸端；居乡不可崖岸太高，要使人易见，以致旧好。为官当清正，为乡当亲和。",
      "category": "为官"
    },
    {
      "id": 50,
      "quote": "大人不可不畏，畏大人则无放逸之心；小民亦不可不畏，畏小民则无豪横之名。",
      "source": "《菜根谭·敬畏篇》",
      "fullText": "大人不可不畏，畏大人则无放逸之心；小民亦不可不畏，畏小民则无豪横之名。敬畏之心，无处不在。",
      "category": "敬畏"
    },
    {
      "id": 51,
      "quote": "事稍拂逆，便思不如我的人，则怨尤自消；心稍怠荒，便思胜似我的人，则精神自奋。",
      "source": "《菜根谭·自励篇》",
      "fullText": "事稍拂逆，便思不如我的人，则怨尤自消；心稍怠荒，便思胜似我的人，则精神自奋。比上不足，比下有余。",
      "category": "自励"
    },
    {
      "id": 52,
      "quote": "不可乘喜而轻诺，不可因醉而生嗔，不可乘快而多事，不可因倦而鲜终。",
      "source": "《菜根谭·谨慎篇》",
      "fullText": "不可乘喜而轻诺，不可因醉而生嗔，不可乘快而多事，不可因倦而鲜终。君子当慎言慎行，有始有终。",
      "category": "谨慎"
    },
    {
      "id": 53,
      "quote": "善读书者，要读到手舞足蹈处，方不落筌蹄；善观物者，要观到心融神洽时，方不泥迹象。",
      "source": "《菜根谭·读书篇》",
      "fullText": "善读书者，要读到手舞足蹈处，方不落筌蹄；善观物者，要观到心融神洽时，方不泥迹象。读书贵在领悟，观物贵在神会。",
      "category": "读书"
    },
    {
      "id": 54,
      "quote": "天贤一人以诲众人之愚，而世反逞所长以形人之短；天富一人以济众人之困，而世反挟所有以凌人之贫。",
      "source": "《菜根谭·天道篇》",
      "fullText": "天贤一人以诲众人之愚，而世反逞所长以形人之短；天富一人以济众人之困，而世反挟所有以凌人之贫。天道无私，人道有私。",
      "category": "天道"
    },
    {
      "id": 55,
      "quote": "至人何思何虑，愚人不识不知，可与论学亦可与建功。唯中材的人，多一番思虑知识，便多一番臆度猜疑，事事难于下手。",
      "source": "《菜根谭·人才篇》",
      "fullText": "至人何思何虑，愚人不识不知，可与论学亦可与建功。唯中材的人，多一番思虑知识，便多一番臆度猜疑，事事难于下手。人才各异，各有所长。",
      "category": "人才"
    },
    {
      "id": 56,
      "quote": "口乃心之门，守口不密，泄尽真机；意乃心之足，防意不严，走尽邪蹊。",
      "source": "《菜根谭·守口篇》",
      "fullText": "口乃心之门，守口不密，泄尽真机；意乃心之足，防意不严，走尽邪蹊。祸从口出，慎言为要。",
      "category": "守口"
    },
    {
      "id": 57,
      "quote": "攻人之恶毋太严，要思其堪受；教人以善毋过高，当使其可从。",
      "source": "《菜根谭·教化篇》",
      "fullText": "攻人之恶毋太严，要思其堪受；教人以善毋过高，当使其可从。教化之道，循序渐进。",
      "category": "教化"
    },
    {
      "id": 58,
      "quote": "粪虫至秽变为蝉，而饮露于秋风；腐草无光化为萤，而耀彩于夏月。",
      "source": "《菜根谭·转化篇》",
      "fullText": "粪虫至秽变为蝉，而饮露于秋风；腐草无光化为萤，而耀彩于夏月。故知洁常自污出，明每从暗生也。",
      "category": "转化"
    },
    {
      "id": 59,
      "quote": "矜高倨傲，无非客气降伏得，客气下而后正气伸；情欲意识，尽属妄心消杀得，妄心尽而后真心现。",
      "source": "《菜根谭·真心篇》",
      "fullText": "矜高倨傲，无非客气降伏得，客气下而后正气伸；情欲意识，尽属妄心消杀得，妄心尽而后真心现。去伪存真，返璞归真。",
      "category": "真心"
    },
    {
      "id": 60,
      "quote": "饱后思味，则浓淡之境都消；色后思淫，则男女之见尽绝。",
      "source": "《菜根谭·节制篇》",
      "fullText": "饱后思味，则浓淡之境都消；色后思淫，则男女之见尽绝。故人常以事后之悔悟，破临事之痴迷，则性定而动无不正。",
      "category": "节制"
    },
    {
      "id": 61,
      "quote": "欲路上事，毋乐其便而姑为染指，一染指便深入万仞；理路上事，毋惮其难而稍为退步，一退步便远隔千山。",
      "source": "《菜根谭·立志篇》",
      "fullText": "欲路上事，毋乐其便而姑为染指，一染指便深入万仞；理路上事，毋惮其难而稍为退步，一退步便远隔千山。立志易，守志难。",
      "category": "立志"
    },
    {
      "id": 62,
      "quote": "为恶而畏人知，恶中犹有善路；为善而急人知，善处即是恶根。",
      "source": "《菜根谭·善恶篇》",
      "fullText": "为恶而畏人知，恶中犹有善路；为善而急人知，善处即是恶根。善恶之分，在乎本心。",
      "category": "善恶"
    },
    {
      "id": 63,
      "quote": "念头宽厚的，如春风煦育，万物遭之而生；念头忌刻的，如朔雪阴凝，万物遭之而死。",
      "source": "《菜根谭·心念篇》",
      "fullText": "念头宽厚的，如春风煦育，万物遭之而生；念头忌刻的，如朔雪阴凝，万物遭之而死。心念不同，结果迥异。",
      "category": "心念"
    },
    {
      "id": 64,
      "quote": "毋因群疑而阻独见，毋任己意而废人言，毋私小惠而伤大体，毋借公论以快私情。",
      "source": "《菜根谭·公正篇》",
      "fullText": "毋因群疑而阻独见，毋任己意而废人言，毋私小惠而伤大体，毋借公论以快私情。公正无私，方能服众。",
      "category": "公正"
    },
    {
      "id": 65,
      "quote": "善人未能急亲不宜预扬，恐来谗谮之奸；恶人未能轻去不宜先发，恐遭媒孽之祸。",
      "source": "《菜根谭·谨慎篇》",
      "fullText": "善人未能急亲不宜预扬，恐来谗谮之奸；恶人未能轻去不宜先发，恐遭媒孽之祸。谨慎行事，方保无虞。",
      "category": "谨慎"
    },
    {
      "id": 66,
      "quote": "青天白日的节义，自暗室屋漏中培来；旋乾转坤的经纶，自临深履薄处缲出。",
      "source": "《菜根谭·根基篇》",
      "fullText": "青天白日的节义，自暗室屋漏中培来；旋乾转坤的经纶，自临深履薄处缲出。根基深厚，方能成就大事。",
      "category": "根基"
    },
    {
      "id": 67,
      "quote": "父慈子孝，兄友弟恭，纵做到极处，俱是合当如此，着不得一毫感激的念头。",
      "source": "《菜根谭·家庭篇》",
      "fullText": "父慈子孝，兄友弟恭，纵做到极处，俱是合当如此，着不得一毫感激的念头。如施者任德，受者怀恩，便是路人，便成市道矣。",
      "category": "家庭"
    },
    {
      "id": 68,
      "quote": "有妍必有丑为之对，我不夸妍，谁能丑我？有洁必有污为之仇，我不好洁，谁能污我？",
      "source": "《菜根谭·相对篇》",
      "fullText": "有妍必有丑为之对，我不夸妍，谁能丑我？有洁必有污为之仇，我不好洁，谁能污我？相对而存，无分别心。",
      "category": "相对"
    },
    {
      "id": 69,
      "quote": "炎凉之态，富贵更甚于贫贱；妒忌之心，骨肉尤狠于外人。",
      "source": "《菜根谭·人情篇》",
      "fullText": "炎凉之态，富贵更甚于贫贱；妒忌之心，骨肉尤狠于外人。此处若不当以冷肠，御以平气，鲜不日坐烦恼障中矣。",
      "category": "人情"
    },
    {
      "id": 70,
      "quote": "功过不容少混，混则人怀惰隳之心；恩仇不可太明，明则人起携贰之志。",
      "source": "《菜根谭·管理篇》",
      "fullText": "功过不容少混，混则人怀惰隳之心；恩仇不可太明，明则人起携贰之志。赏罚分明，恩威并施。",
      "category": "管理"
    },
    {
      "id": 71,
      "quote": "爵位不宜太盛，太盛则危；能事不宜尽毕，尽毕则衰；行谊不宜过高，过高则谤兴而毁来。",
      "source": "《菜根谭·中庸篇》",
      "fullText": "爵位不宜太盛，太盛则危；能事不宜尽毕，尽毕则衰；行谊不宜过高，过高则谤兴而毁来。中庸之道，贵在适度。",
      "category": "中庸"
    },
    {
      "id": 72,
      "quote": "恶忌阴，善忌阳。故恶之显者祸浅，而隐者祸深；善之显者功小，而隐者功大。",
      "source": "《菜根谭·隐显篇》",
      "fullText": "恶忌阴，善忌阳。故恶之显者祸浅，而隐者祸深；善之显者功小，而隐者功大。善行无形，恶行无痕。",
      "category": "隐显"
    },
    {
      "id": 73,
      "quote": "德者才之主，才者德之奴。有才无德，如家无主而奴用事矣，几何不魍魉猖狂。",
      "source": "《菜根谭·德才篇》",
      "fullText": "德者才之主，才者德之奴。有才无德，如家无主而奴用事矣，几何不魍魉猖狂。德才兼备，方为人才。",
      "category": "德才"
    },
    {
      "id": 74,
      "quote": "锄奸杜幸，要放他一条去路。若使之一无所容，譬如塞鼠穴者，一切去路都塞尽，则一切好物俱咬破矣。",
      "source": "《菜根谭·宽容篇》",
      "fullText": "锄奸杜幸，要放他一条去路。若使之一无所容，譬如塞鼠穴者，一切去路都塞尽，则一切好物俱咬破矣。网开一面，方为上策。",
      "category": "宽容"
    },
    {
      "id": 75,
      "quote": "当与人同过，不当与人同功，同功则相忌；可与人共患难，不可与人共安乐，安乐则相仇。",
      "source": "《菜根谭·共事篇》",
      "fullText": "当与人同过，不当与人同功，同功则相忌；可与人共患难，不可与人共安乐，安乐则相仇。共事之道，贵在知进退。",
      "category": "共事"
    },
    {
      "id": 76,
      "quote": "饥则附，饱则飏，燠则趋，寒则弃，人情通患也。",
      "source": "《菜根谭·人情篇》",
      "fullText": "饥则附，饱则飏，燠则趋，寒则弃，人情通患也。世态炎凉，古今同慨。",
      "category": "人情"
    },
    {
      "id": 77,
      "quote": "君子宜净拭冷眼，慎勿轻动刚肠。",
      "source": "《菜根谭·冷静篇》",
      "fullText": "君子宜净拭冷眼，慎勿轻动刚肠。冷静观察，理性判断。",
      "category": "冷静"
    },
    {
      "id": 78,
      "quote": "德随量进，量由识长。故欲厚其德，不可不弘其量；欲弘其量，不可不大其识。",
      "source": "《菜根谭·修养篇》",
      "fullText": "德随量进，量由识长。故欲厚其德，不可不弘其量；欲弘其量，不可不大其识。德量识三者，相辅相成。",
      "category": "修养"
    },
    {
      "id": 79,
      "quote": "一苦一乐相磨练，练极而成福者其福始久；一疑一信相参勘，勘极而成知者其知始真。",
      "source": "《菜根谭·磨练篇》",
      "fullText": "一苦一乐相磨练，练极而成福者其福始久；一疑一信相参勘，勘极而成知者其知始真。真知灼见，来自实践。",
      "category": "磨练"
    },
    {
      "id": 80,
      "quote": "地之秽者多生物，水之清者常无鱼。故君子当存含垢纳污之量，不可持好洁独行之操。",
      "source": "《菜根谭·包容篇》",
      "fullText": "地之秽者多生物，水之清者常无鱼。故君子当存含垢纳污之量，不可持好洁独行之操。包容万物，方成其大。",
      "category": "包容"
    },
    {
      "id": 81,
      "quote": "钓水逸事也，尚持生杀之柄；弈棋清戏也，且动战争之心。",
      "source": "《菜根谭·游戏篇》",
      "fullText": "钓水逸事也，尚持生杀之柄；弈棋清戏也，且动战争之心。可见喜事不如省事之为适，多能不如无能之全真。",
      "category": "游戏"
    },
    {
      "id": 82,
      "quote": "莺花茂而山浓谷艳，总是乾坤之幻境；水木落而石瘦崖枯，才见天地之真吾。",
      "source": "《菜根谭·真幻篇》",
      "fullText": "莺花茂而山浓谷艳，总是乾坤之幻境；水木落而石瘦崖枯，才见天地之真吾。四季轮回，见真见幻。",
      "category": "真幻"
    },
    {
      "id": 83,
      "quote": "岁月本长，而忙者自促；天地本宽，而鄙者自隘；风花雪月本闲，而扰攘者自冗。",
      "source": "《菜根谭·心境篇》",
      "fullText": "岁月本长，而忙者自促；天地本宽，而鄙者自隘；风花雪月本闲，而扰攘者自冗。心静自然天地宽。",
      "category": "心境"
    },
    {
      "id": 84,
      "quote": "得趣不在多，盆池拳石间烟霞俱足；会景不在远，蓬窗竹屋下风月自赊。",
      "source": "《菜根谭·趣境篇》",
      "fullText": "得趣不在多，盆池拳石间烟霞俱足；会景不在远，蓬窗竹屋下风月自赊。境由心造，趣在自得。",
      "category": "趣境"
    },
    {
      "id": 85,
      "quote": "心无物欲，即是秋空霁海；坐有琴书，便成石室丹丘。",
      "source": "《菜根谭·心境篇》",
      "fullText": "心无物欲，即是秋空霁海；坐有琴书，便成石室丹丘。清心寡欲，雅趣自来。",
      "category": "心境"
    },
    {
      "id": 86,
      "quote": "宠辱不惊，闲看庭前花开花落；去留无意，漫随天外云卷云舒。",
      "source": "《菜根谭·闲适篇》",
      "fullText": "宠辱不惊，闲看庭前花开花落；去留无意，漫随天外云卷云舒。人当超然物外，不为外物所累，心自安闲。",
      "category": "闲适"
    },
    {
      "id": 87,
      "quote": "水流任意境常静，花落虽频意自闲。",
      "source": "《菜根谭·静闲篇》",
      "fullText": "水流任意境常静，花落虽频意自闲。人生在世，当如水流花落，随缘而安。",
      "category": "静闲"
    },
    {
      "id": 88,
      "quote": "竹篱下，忽闻犬吠鸡鸣，恍似云中世界；芸窗中，雅听蝉吟鸦噪，方知静里乾坤。",
      "source": "《菜根谭·静境篇》",
      "fullText": "竹篱下，忽闻犬吠鸡鸣，恍似云中世界；芸窗中，雅听蝉吟鸦噪，方知静里乾坤。静中见动，动中见静。",
      "category": "静境"
    },
    {
      "id": 89,
      "quote": "山林是胜地，一营恋便成市朝；书画是雅事，一贪痴便成商贾。",
      "source": "《菜根谭·雅俗篇》",
      "fullText": "山林是胜地，一营恋便成市朝；书画是雅事，一贪痴便成商贾。凡事过度，雅亦成俗。",
      "category": "雅俗"
    },
    {
      "id": 90,
      "quote": "诗思在灞陵桥上，微吟就，林岫便已浩然；野兴在镜湖曲边，独往时，山川自相映发。",
      "source": "《菜根谭·诗兴篇》",
      "fullText": "诗思在灞陵桥上，微吟就，林岫便已浩然；野兴在镜湖曲边，独往时，山川自相映发。诗兴野趣，天人合一。",
      "category": "诗兴"
    },
    {
      "id": 91,
      "quote": "芦花被下，卧雪眠云，保全得一窝夜气；竹叶杯中，吟风弄月，躲离了万丈红尘。",
      "source": "《菜根谭·隐逸篇》",
      "fullText": "芦花被下，卧雪眠云，保全得一窝夜气；竹叶杯中，吟风弄月，躲离了万丈红尘。隐逸之乐，清净自在。",
      "category": "隐逸"
    },
    {
      "id": 92,
      "quote": "衮冕行中，著一藜杖的山人，便增一段高风；渔樵路上，著一衮衣的朝士，转添许多俗气。",
      "source": "《菜根谭·风雅篇》",
      "fullText": "衮冕行中，著一藜杖的山人，便增一段高风；渔樵路上，著一衮衣的朝士，转添许多俗气。雅俗相衬，境界自现。",
      "category": "风雅"
    },
    {
      "id": 93,
      "quote": "竹窗下，惟有蝉吟鹊噪，方知静里乾坤；茶灶边，时听松涛竹韵，顿觉胸中块垒。",
      "source": "《菜根谭·静境篇》",
      "fullText": "竹窗下，惟有蝉吟鹊噪，方知静里乾坤；茶灶边，时听松涛竹韵，顿觉胸中块垒。静中得趣，胸次洒然。",
      "category": "静境"
    },
    {
      "id": 94,
      "quote": "松涧边，携杖独行，立处云生破衲；竹窗下，枕书高卧，觉时月侵寒毡。",
      "source": "《菜根谭·隐居篇》",
      "fullText": "松涧边，携杖独行，立处云生破衲；竹窗下，枕书高卧，觉时月侵寒毡。隐居之乐，超然物外。",
      "category": "隐居"
    },
    {
      "id": 95,
      "quote": "忽睹天际彩云，常疑好事皆虚事；再观山中古木，方信闲人是福人。",
      "source": "《菜根谭·福祸篇》",
      "fullText": "忽睹天际彩云，常疑好事皆虚事；再观山中古木，方信闲人是福人。虚中有实，闲中得福。",
      "category": "福祸"
    },
    {
      "id": 96,
      "quote": "霜天闻鹤唳，雪夜听鸡鸣，得乾坤清纯之气；晴空看鸟飞，活水观鱼戏，识宇宙活泼之机。",
      "source": "《菜根谭·生机篇》",
      "fullText": "霜天闻鹤唳，雪夜听鸡鸣，得乾坤清纯之气；晴空看鸟飞，活水观鱼戏，识宇宙活泼之机。自然生机，随处可得。",
      "category": "生机"
    },
    {
      "id": 97,
      "quote": "芳菲园林看蜂忙，觑破几般尘情世态；寂寞衡茅观燕寝，引起一种冷趣幽思。",
      "source": "《菜根谭·观物篇》",
      "fullText": "芳菲园林看蜂忙，觑破几般尘情世态；寂寞衡茅观燕寝，引起一种冷趣幽思。观物得理，冷眼热心。",
      "category": "观物"
    },
    {
      "id": 98,
      "quote": "会心不在远，得趣不在多。盆池拳石间，便居然有万里山川之势，片言只语内，便宛然见万古圣贤之心。",
      "source": "《菜根谭·会心篇》",
      "fullText": "会心不在远，得趣不在多。盆池拳石间，便居然有万里山川之势，片言只语内，便宛然见万古圣贤之心。小中见大，微中见著。",
      "category": "会心"
    },
    {
      "id": 99,
      "quote": "心地上无风涛，随在皆青山绿水；性天中有化育，触处见鱼跃鸢飞。",
      "source": "《菜根谭·性天篇》",
      "fullText": "心地上无风涛，随在皆青山绿水；性天中有化育，触处见鱼跃鸢飞。心地平和，万物皆春。",
      "category": "性天"
    },
    {
      "id": 100,
      "quote": "鱼得水逝而相忘乎水，鸟乘风飞而不知有风。",
      "source": "《菜根谭·自然篇》",
      "fullText": "鱼得水逝而相忘乎水，鸟乘风飞而不知有风。识此可以超物累，可以乐天机。",
      "category": "自然"
    },
    {
      "id": 101,
      "quote": "狐眠败砌，兔走荒台，尽是当年歌舞之地；露冷黄花，烟迷衰草，悉属旧时争战之场。",
      "source": "《菜根谭·沧桑篇》",
      "fullText": "狐眠败砌，兔走荒台，尽是当年歌舞之地；露冷黄花，烟迷衰草，悉属旧时争战之场。盛衰无常，古今同慨。",
      "category": "沧桑"
    },
    {
      "id": 102,
      "quote": "秋虫春鸟共畅天机，何必浪生悲喜；老树新花同含生意，胡为妄别媸妍。",
      "source": "《菜根谭·生意篇》",
      "fullText": "秋虫春鸟共畅天机，何必浪生悲喜；老树新花同含生意，胡为妄别媸妍。万物平等，各得其妙。",
      "category": "生意"
    },
    {
      "id": 103,
      "quote": "昼闲人寂，听数声鸟语悠扬，不觉耳根尽彻；夜静天高，看一片云光舒卷，顿令眼界俱空。",
      "source": "《菜根谭·静观篇》",
      "fullText": "昼闲人寂，听数声鸟语悠扬，不觉耳根尽彻；夜静天高，看一片云光舒卷，顿令眼界俱空。静观自得，心地空明。",
      "category": "静观"
    },
    {
      "id": 104,
      "quote": "登高使人心旷，临流使人意远；读书于雨雪之夜，使人神清；舒啸于丘阜之巅，使人兴迈。",
      "source": "《菜根谭·登临篇》",
      "fullText": "登高使人心旷，临流使人意远；读书于雨雪之夜，使人神清；舒啸于丘阜之巅，使人兴迈。登临之乐，心境开阔。",
      "category": "登临"
    },
    {
      "id": 105,
      "quote": "心旷则万钟如瓦缶，心隘则一发似车轮。",
      "source": "《菜根谭·心胸篇》",
      "fullText": "心旷则万钟如瓦缶，心隘则一发似车轮。心境不同，物亦随之。",
      "category": "心胸"
    },
    {
      "id": 106,
      "quote": "无风月花柳不成造化，无情欲嗜好不成心体。",
      "source": "《菜根谭·造化篇》",
      "fullText": "无风月花柳不成造化，无情欲嗜好不成心体。只以我转物，不以物役我，则嗜欲莫非天机，尘情即是理境。",
      "category": "造化"
    },
    {
      "id": 107,
      "quote": "就一身了一身者，方能以万物付万物；还天下于天下者，方能出世间于世间。",
      "source": "《菜根谭·出世篇》",
      "fullText": "就一身了一身者，方能以万物付万物；还天下于天下者，方能出世间于世间。超然物外，返璞归真。",
      "category": "出世"
    },
    {
      "id": 108,
      "quote": "人生太闲则别念窃生，太忙则真性不现。",
      "source": "《菜根谭·闲忙篇》",
      "fullText": "人生太闲则别念窃生，太忙则真性不现。故士君子不可不抱身心之忧，亦不可不耽风月之趣。",
      "category": "闲忙"
    },
    {
      "id": 109,
      "quote": "君子之心事，天青日白，不可使人不知；君子之才华，玉韫珠藏，不可使人易知。",
      "source": "《菜根谭·君子篇》",
      "fullText": "君子之心事，天青日白，不可使人不知；君子之才华，玉韫珠藏，不可使人易知。心迹明朗，才华内敛。",
      "category": "君子"
    },
    {
      "id": 110,
      "quote": "耳中常闻逆耳之言，心中常有拂心之事，才是进德修行的砥石。",
      "source": "《菜根谭·修身篇》",
      "fullText": "耳中常闻逆耳之言，心中常有拂心之事，才是进德修行的砥石。若言言悦耳，事事快心，便把此生理在鸩毒中矣。",
      "category": "修身"
    },
    {
      "id": 111,
      "quote": "疾风怒雨，禽鸟戚戚；霁日光风，草木欣欣。",
      "source": "《菜根谭·气象篇》",
      "fullText": "疾风怒雨，禽鸟戚戚；霁日光风，草木欣欣。可见天地不可一日无和气，人心不可一日无喜神。",
      "category": "气象"
    },
    {
      "id": 112,
      "quote": "醲肥辛甘非真味，真味只是淡；神奇卓异非至人，至人只是常。",
      "source": "《菜根谭·真味篇》",
      "fullText": "醲肥辛甘非真味，真味只是淡；神奇卓异非至人，至人只是常。平淡是真，常道最贵。",
      "category": "真味"
    },
    {
      "id": 113,
      "quote": "天地寂然不动，而气机无息稍停；日月尽夜奔驰，而贞明万古不易。",
      "source": "《菜根谭·天道篇》",
      "fullText": "天地寂然不动，而气机无息稍停；日月尽夜奔驰，而贞明万古不易。故君子闲时要有吃紧的心思，忙处要有悠闲的趣味。",
      "category": "天道"
    },
    {
      "id": 114,
      "quote": "恩里由来生害，故快意时须早回头；败后或反成功，故拂心处切莫放手。",
      "source": "《菜根谭·成败篇》",
      "fullText": "恩里由来生害，故快意时须早回头；败后或反成功，故拂心处切莫放手。成败相因，祸福相倚。",
      "category": "成败"
    },
    {
      "id": 115,
      "quote": "藜口苋肠者，多冰清玉洁；衮衣玉食者，甘卑躬屈节。",
      "source": "《菜根谭·清浊篇》",
      "fullText": "藜口苋肠者，多冰清玉洁；衮衣玉食者，甘卑躬屈节。盖志以淡泊明，而节从肥甘丧矣。",
      "category": "清浊"
    },
    {
      "id": 116,
      "quote": "面前的田地要放得宽，使人无不平之叹；身后的惠泽要流得久，使人有不匮之思。",
      "source": "《菜根谭·仁德篇》",
      "fullText": "面前的田地要放得宽，使人无不平之叹；身后的惠泽要流得久，使人有不匮之思。如此方可谓达人也。",
      "category": "仁德"
    },
    {
      "id": 117,
      "quote": "路径窄处留一步，与人行；滋味浓的减三分，让人尝。",
      "source": "《菜根谭·谦让篇》",
      "fullText": "路径窄处留一步，与人行；滋味浓的减三分，让人尝。此是涉世一极安乐法，亦是处世一极受用法。",
      "category": "谦让"
    },
    {
      "id": 118,
      "quote": "作人无甚高远的事业，摆脱得俗情便入名流；为学无甚增益的功夫，减除得物累便臻圣境。",
      "source": "《菜根谭·作人篇》",
      "fullText": "作人无甚高远的事业，摆脱得俗情便入名流；为学无甚增益的功夫，减除得物累便臻圣境。简简单单，便是真谛。",
      "category": "作人"
    },
    {
      "id": 119,
      "quote": "宠利毋居人前，德业毋落人后；受享毋逾分外，修持毋减分中。",
      "source": "《菜根谭·进退篇》",
      "fullText": "宠利毋居人前，德业毋落人后；受享毋逾分外，修持毋减分中。进退有度，不失本真。",
      "category": "进退"
    },
    {
      "id": 120,
      "quote": "处世让一步为高，退步即进步的张本；待人宽一分是福，利人实利己的根基。",
      "source": "《菜根谭·处世篇》",
      "fullText": "处世让一步为高，退步即进步的张本；待人宽一分是福，利人实利己的根基。凡事退一步，天地自然宽；待人宽一分，福气自然来。",
      "category": "处世"
    },
    {
      "id": 121,
      "quote": "盖世功劳，当不得一个矜字；弥天罪过，当不得一个悔字。",
      "source": "《菜根谭·功劳篇》",
      "fullText": "盖世功劳，当不得一个矜字；弥天罪过，当不得一个悔字。谦虚谨慎，悔过自新。",
      "category": "功劳"
    },
    {
      "id": 122,
      "quote": "完名美节，不宜独任，分些与人可以远害全身；辱行污名，不宜全推，引些归己可以韬光养德。",
      "source": "《菜根谭·名节篇》",
      "fullText": "完名美节，不宜独任，分些与人可以远害全身；辱行污名，不宜全推，引些归己可以韬光养德。名节之重，不可不慎。",
      "category": "名节"
    },
    {
      "id": 123,
      "quote": "事事要留个有余不尽的意思，便造物不能忌我，鬼神不能损我。",
      "source": "《菜根谭·有余篇》",
      "fullText": "事事要留个有余不尽的意思，便造物不能忌我，鬼神不能损我。若业必求满，功必求盈者，不生内变，必招外忧。",
      "category": "有余"
    },
    {
      "id": 124,
      "quote": "攻人之恶毋太严，要思其堪受；教人以善毋过高，当使其可从。",
      "source": "《菜根谭·教化篇》",
      "fullText": "攻人之恶毋太严，要思其堪受；教人以善毋过高，当使其可从。教化之道，贵在循序渐进。",
      "category": "教化"
    },
    {
      "id": 125,
      "quote": "粪虫至秽变为蝉，而饮露于秋风；腐草无光化为萤，而耀彩于夏月。",
      "source": "《菜根谭·转化篇》",
      "fullText": "粪虫至秽变为蝉，而饮露于秋风；腐草无光化为萤，而耀彩于夏月。故知洁常自污出，明每从暗生也。",
      "category": "转化"
    },
    {
      "id": 126,
      "quote": "矜高倨傲，无非客气降伏得，客气下而后正气伸；情欲意识，尽属妄心消杀得，妄心尽而后真心现。",
      "source": "《菜根谭·真心篇》",
      "fullText": "矜高倨傲，无非客气降伏得，客气下而后正气伸；情欲意识，尽属妄心消杀得，妄心尽而后真心现。去伪存真，返璞归真。",
      "category": "真心"
    },
    {
      "id": 127,
      "quote": "饱后思味，则浓淡之境都消；色后思淫，则男女之见尽绝。",
      "source": "《菜根谭·节制篇》",
      "fullText": "饱后思味，则浓淡之境都消；色后思淫，则男女之见尽绝。故人常以事后之悔悟，破临事之痴迷，则性定而动无不正。",
      "category": "节制"
    },
    {
      "id": 128,
      "quote": "欲路上事，毋乐其便而姑为染指，一染指便深入万仞；理路上事，毋惮其难而稍为退步，一退步便远隔千山。",
      "source": "《菜根谭·立志篇》",
      "fullText": "欲路上事，毋乐其便而姑为染指，一染指便深入万仞；理路上事，毋惮其难而稍为退步，一退步便远隔千山。立志易，守志难。",
      "category": "立志"
    },
    {
      "id": 129,
      "quote": "为恶而畏人知，恶中犹有善路；为善而急人知，善处即是恶根。",
      "source": "《菜根谭·善恶篇》",
      "fullText": "为恶而畏人知，恶中犹有善路；为善而急人知，善处即是恶根。善恶之分，在乎本心。",
      "category": "善恶"
    },
    {
      "id": 130,
      "quote": "念头宽厚的，如春风煦育，万物遭之而生；念头忌刻的，如朔雪阴凝，万物遭之而死。",
      "source": "《菜根谭·心念篇》",
      "fullText": "念头宽厚的，如春风煦育，万物遭之而生；念头忌刻的，如朔雪阴凝，万物遭之而死。心念不同，结果迥异。",
      "category": "心念"
    },
    {
      "id": 131,
      "quote": "毋因群疑而阻独见，毋任己意而废人言，毋私小惠而伤大体，毋借公论以快私情。",
      "source": "《菜根谭·公正篇》",
      "fullText": "毋因群疑而阻独见，毋任己意而废人言，毋私小惠而伤大体，毋借公论以快私情。公正无私，方能服众。",
      "category": "公正"
    },
    {
      "id": 132,
      "quote": "善人未能急亲不宜预扬，恐来谗谮之奸；恶人未能轻去不宜先发，恐遭媒孽之祸。",
      "source": "《菜根谭·谨慎篇》",
      "fullText": "善人未能急亲不宜预扬，恐来谗谮之奸；恶人未能轻去不宜先发，恐遭媒孽之祸。谨慎行事，方保无虞。",
      "category": "谨慎"
    },
    {
      "id": 133,
      "quote": "青天白日的节义，自暗室屋漏中培来；旋乾转坤的经纶，自临深履薄处缲出。",
      "source": "《菜根谭·根基篇》",
      "fullText": "青天白日的节义，自暗室屋漏中培来；旋乾转坤的经纶，自临深履薄处缲出。根基深厚，方能成就大事。",
      "category": "根基"
    },
    {
      "id": 134,
      "quote": "父慈子孝，兄友弟恭，纵做到极处，俱是合当如此，着不得一毫感激的念头。",
      "source": "《菜根谭·家庭篇》",
      "fullText": "父慈子孝，兄友弟恭，纵做到极处，俱是合当如此，着不得一毫感激的念头。如施者任德，受者怀恩，便是路人，便成市道矣。",
      "category": "家庭"
    },
    {
      "id": 135,
      "quote": "有妍必有丑为之对，我不夸妍，谁能丑我？有洁必有污为之仇，我不好洁，谁能污我？",
      "source": "《菜根谭·相对篇》",
      "fullText": "有妍必有丑为之对，我不夸妍，谁能丑我？有洁必有污为之仇，我不好洁，谁能污我？相对而存，无分别心。",
      "category": "相对"
    },
    {
      "id": 136,
      "quote": "炎凉之态，富贵更甚于贫贱；妒忌之心，骨肉尤狠于外人。",
      "source": "《菜根谭·人情篇》",
      "fullText": "炎凉之态，富贵更甚于贫贱；妒忌之心，骨肉尤狠于外人。此处若不当以冷肠，御以平气，鲜不日坐烦恼障中矣。",
      "category": "人情"
    },
    {
      "id": 137,
      "quote": "功过不容少混，混则人怀惰隳之心；恩仇不可太明，明则人起携贰之志。",
      "source": "《菜根谭·管理篇》",
      "fullText": "功过不容少混，混则人怀惰隳之心；恩仇不可太明，明则人起携贰之志。赏罚分明，恩威并施。",
      "category": "管理"
    },
    {
      "id": 138,
      "quote": "爵位不宜太盛，太盛则危；能事不宜尽毕，尽毕则衰；行谊不宜过高，过高则谤兴而毁来。",
      "source": "《菜根谭·中庸篇》",
      "fullText": "爵位不宜太盛，太盛则危；能事不宜尽毕，尽毕则衰；行谊不宜过高，过高则谤兴而毁来。中庸之道，贵在适度。",
      "category": "中庸"
    },
    {
      "id": 139,
      "quote": "恶忌阴，善忌阳。故恶之显者祸浅，而隐者祸深；善之显者功小，而隐者功大。",
      "source": "《菜根谭·隐显篇》",
      "fullText": "恶忌阴，善忌阳。故恶之显者祸浅，而隐者祸深；善之显者功小，而隐者功大。善行无形，恶行无痕。",
      "category": "隐显"
    },
    {
      "id": 140,
      "quote": "德者才之主，才者德之奴。有才无德，如家无主而奴用事矣，几何不魍魉猖狂。",
      "source": "《菜根谭·德才篇》",
      "fullText": "德者才之主，才者德之奴。有才无德，如家无主而奴用事矣，几何不魍魉猖狂。德才兼备，方为人才。",
      "category": "德才"
    },
    {
      "id": 141,
      "quote": "锄奸杜幸，要放他一条去路。若使之一无所容，譬如塞鼠穴者，一切去路都塞尽，则一切好物俱咬破矣。",
      "source": "《菜根谭·宽容篇》",
      "fullText": "锄奸杜幸，要放他一条去路。若使之一无所容，譬如塞鼠穴者，一切去路都塞尽，则一切好物俱咬破矣。网开一面，方为上策。",
      "category": "宽容"
    },
    {
      "id": 142,
      "quote": "当与人同过，不当与人同功，同功则相忌；可与人共患难，不可与人共安乐，安乐则相仇。",
      "source": "《菜根谭·共事篇》",
      "fullText": "当与人同过，不当与人同功，同功则相忌；可与人共患难，不可与人共安乐，安乐则相仇。共事之道，贵在知进退。",
      "category": "共事"
    },
    {
      "id": 143,
      "quote": "饥则附，饱则飏，燠则趋，寒则弃，人情通患也。",
      "source": "《菜根谭·人情篇》",
      "fullText": "饥则附，饱则飏，燠则趋，寒则弃，人情通患也。世态炎凉，古今同慨。",
      "category": "人情"
    },
    {
      "id": 144,
      "quote": "君子宜净拭冷眼，慎勿轻动刚肠。",
      "source": "《菜根谭·冷静篇》",
      "fullText": "君子宜净拭冷眼，慎勿轻动刚肠。冷静观察，理性判断。",
      "category": "冷静"
    },
    {
      "id": 145,
      "quote": "德随量进，量由识长。故欲厚其德，不可不弘其量；欲弘其量，不可不大其识。",
      "source": "《菜根谭·修养篇》",
      "fullText": "德随量进，量由识长。故欲厚其德，不可不弘其量；欲弘其量，不可不大其识。德量识三者，相辅相成。",
      "category": "修养"
    },
    {
      "id": 146,
      "quote": "一苦一乐相磨练，练极而成福者其福始久；一疑一信相参勘，勘极而成知者其知始真。",
      "source": "《菜根谭·磨练篇》",
      "fullText": "一苦一乐相磨练，练极而成福者其福始久；一疑一信相参勘，勘极而成知者其知始真。真知灼见，来自实践。",
      "category": "磨练"
    },
    {
      "id": 147,
      "quote": "地之秽者多生物，水之清者常无鱼。故君子当存含垢纳污之量，不可持好洁独行之操。",
      "source": "《菜根谭·包容篇》",
      "fullText": "地之秽者多生物，水之清者常无鱼。故君子当存含垢纳污之量，不可持好洁独行之操。包容万物，方成其大。",
      "category": "包容"
    },
    {
      "id": 148,
      "quote": "泛驾之马可就驰驱，跃冶之金终归型范。",
      "source": "《菜根谭·型范篇》",
      "fullText": "泛驾之马可就驰驱，跃冶之金终归型范。只一优游不振，便终身无个进步。",
      "category": "型范"
    },
    {
      "id": 149,
      "quote": "人只一念贪私，便销刚为柔，塞智为昏，变恩为惨，染洁为污，坏了一生人品。",
      "source": "《菜根谭·贪私篇》",
      "fullText": "人只一念贪私，便销刚为柔，塞智为昏，变恩为惨，染洁为污，坏了一生人品。故古人以不贪为宝，所以度越一世。",
      "category": "贪私"
    },
    {
      "id": 150,
      "quote": "耳目见闻为外贼，情欲意识为内贼。",
      "source": "《菜根谭·内外篇》",
      "fullText": "耳目见闻为外贼，情欲意识为内贼。只是主人翁惺惺不昧，独坐中堂，贼便化为家人矣。",
      "category": "内外"
    },
    {
      "id": 151,
      "quote": "图未就之功，不如保已成之业；悔既往之失，不如防将来之非。",
      "source": "《菜根谭·功业篇》",
      "fullText": "图未就之功，不如保已成之业；悔既往之失，不如防将来之非。务实求稳，着眼未来。",
      "category": "功业"
    },
    {
      "id": 152,
      "quote": "气象要高旷，而不可疏狂；心思要缜密，而不可琐屑；趣味要冲淡，而不可偏枯；操守要严明，而不可激烈。",
      "source": "《菜根谭·气象篇》",
      "fullText": "气象要高旷，而不可疏狂；心思要缜密，而不可琐屑；趣味要冲淡，而不可偏枯；操守要严明，而不可激烈。凡事贵在适度。",
      "category": "气象"
    },
    {
      "id": 153,
      "quote": "风来疏竹，风过而竹不留声；雁渡寒潭，雁去而潭不留影。",
      "source": "《菜根谭·心境篇》",
      "fullText": "风来疏竹，风过而竹不留声；雁渡寒潭，雁去而潭不留影。故君子事来而心始现，事去而心随空。",
      "category": "心境"
    },
    {
      "id": 154,
      "quote": "清能有容，仁能善断，明不伤察，直不过矫，是谓蜜饯不甜，海味不咸，才是懿德。",
      "source": "《菜根谭·懿德篇》",
      "fullText": "清能有容，仁能善断，明不伤察，直不过矫，是谓蜜饯不甜，海味不咸，才是懿德。中庸之道，恰到好处。",
      "category": "懿德"
    },
    {
      "id": 155,
      "quote": "贫家净扫地，贫女净梳头，景色虽不艳丽，气度自是风雅。",
      "source": "《菜根谭·风雅篇》",
      "fullText": "贫家净扫地，贫女净梳头，景色虽不艳丽，气度自是风雅。士君子一当穷愁寥落，奈何辄自废弛哉！",
      "category": "风雅"
    },
    {
      "id": 156,
      "quote": "学者有段兢业的心思，又要有段潇洒的趣味。",
      "source": "《菜根谭·治学篇》",
      "fullText": "学者有段兢业的心思，又要有段潇洒的趣味。若一味敛束清苦，是有秋杀无春生，何以发育万物？",
      "category": "治学"
    },
    {
      "id": 157,
      "quote": "真廉无廉名，立名者正所以为贪；大巧无巧术，用术者乃所以为拙。",
      "source": "《菜根谭·真伪篇》",
      "fullText": "真廉无廉名，立名者正所以为贪；大巧无巧术，用术者乃所以为拙。真伪之辨，在于本心。",
      "category": "真伪"
    },
    {
      "id": 158,
      "quote": "欹器以满覆，扑满以空全；故君子宁居无不居有，宁处缺不处完。",
      "source": "《菜根谭·盈亏篇》",
      "fullText": "欹器以满覆，扑满以空全；故君子宁居无不居有，宁处缺不处完。满招损，谦受益。",
      "category": "盈亏"
    },
    {
      "id": 159,
      "quote": "名根未拔者，纵轻千乘甘一瓢，总堕尘情；客气未融者，虽泽四海利万世，终为剩技。",
      "source": "《菜根谭·名根篇》",
      "fullText": "名根未拔者，纵轻千乘甘一瓢，总堕尘情；客气未融者，虽泽四海利万世，终为剩技。去名根，融客气，方见真功夫。",
      "category": "名根"
    },
    {
      "id": 160,
      "quote": "人心有部真文章，都被残编断简封固了；有部真鼓吹，都被妖歌艳舞湮没了。",
      "source": "《菜根谭·真文章篇》",
      "fullText": "人心有部真文章，都被残编断简封固了；有部真鼓吹，都被妖歌艳舞湮没了。学者须扫除外物，直觅本来，才有个真受用。",
      "category": "真文章"
    },
    {
      "id": 161,
      "quote": "天理路上甚宽，稍游心胸中便觉广大宏朗；人欲路上甚窄，才寄迹眼前俱是荆棘泥涂。",
      "source": "《菜根谭·天理篇》",
      "fullText": "天理路上甚宽，稍游心胸中便觉广大宏朗；人欲路上甚窄，才寄迹眼前俱是荆棘泥涂。天理人欲，泾渭分明。",
      "category": "天理"
    },
    {
      "id": 162,
      "quote": "一疑一信相参勘，勘极而成知者其知始真。",
      "source": "《菜根谭·知真篇》",
      "fullText": "一疑一信相参勘，勘极而成知者其知始真。真知来自于不断的探索和验证。",
      "category": "知真"
    },
    {
      "id": 163,
      "quote": "欲路上事，毋乐其便而姑为染指，一染指便深入万仞。",
      "source": "《菜根谭·欲路篇》",
      "fullText": "欲路上事，毋乐其便而姑为染指，一染指便深入万仞。欲海无边，回头是岸。",
      "category": "欲路"
    },
    {
      "id": 164,
      "quote": "理路上事，毋惮其难而稍为退步，一退步便远隔千山。",
      "source": "《菜根谭·理路篇》",
      "fullText": "理路上事，毋惮其难而稍为退步，一退步便远隔千山。真理之路，勇往直前。",
      "category": "理路"
    },
    {
      "id": 165,
      "quote": "为恶而畏人知，恶中犹有善路。",
      "source": "《菜根谭·善恶篇》",
      "fullText": "为恶而畏人知，恶中犹有善路。心存敬畏，尚有可为。",
      "category": "善恶"
    },
    {
      "id": 166,
      "quote": "为善而急人知，善处即是恶根。",
      "source": "《菜根谭·善恶篇》",
      "fullText": "为善而急人知，善处即是恶根。伪善之心，害人害己。",
      "category": "善恶"
    },
    {
      "id": 167,
      "quote": "念头宽厚的，如春风煦育，万物遭之而生。",
      "source": "《菜根谭·心念篇》",
      "fullText": "念头宽厚的，如春风煦育，万物遭之而生。心念宽厚，福泽深厚。",
      "category": "心念"
    },
    {
      "id": 168,
      "quote": "念头忌刻的，如朔雪阴凝，万物遭之而死。",
      "source": "《菜根谭·心念篇》",
      "fullText": "念头忌刻的，如朔雪阴凝，万物遭之而死。心念刻薄，伤人伤己。",
      "category": "心念"
    },
    {
      "id": 169,
      "quote": "毋因群疑而阻独见，毋任己意而废人言。",
      "source": "《菜根谭·公正篇》",
      "fullText": "毋因群疑而阻独见，毋任己意而废人言。虚心纳谏，明辨是非。",
      "category": "公正"
    },
    {
      "id": 170,
      "quote": "毋私小惠而伤大体，毋借公论以快私情。",
      "source": "《菜根谭·公正篇》",
      "fullText": "毋私小惠而伤大体，毋借公论以快私情。公正无私，方能服众。",
      "category": "公正"
    },
    {
      "id": 171,
      "quote": "善人未能急亲不宜预扬，恐来谗谮之奸。",
      "source": "《菜根谭·谨慎篇》",
      "fullText": "善人未能急亲不宜预扬，恐来谗谮之奸。谨慎交友，免受其害。",
      "category": "谨慎"
    },
    {
      "id": 172,
      "quote": "恶人未能轻去不宜先发，恐遭媒孽之祸。",
      "source": "《菜根谭·谨慎篇》",
      "fullText": "恶人未能轻去不宜先发，恐遭媒孽之祸。谨慎行事，避免祸端。",
      "category": "谨慎"
    },
    {
      "id": 173,
      "quote": "青天白日的节义，自暗室屋漏中培来。",
      "source": "《菜根谭·根基篇》",
      "fullText": "青天白日的节义，自暗室屋漏中培来。真功夫在无人处。",
      "category": "根基"
    },
    {
      "id": 174,
      "quote": "旋乾转坤的经纶，自临深履薄处缲出。",
      "source": "《菜根谭·根基篇》",
      "fullText": "旋乾转坤的经纶，自临深履薄处缲出。大智慧在谨慎中。",
      "category": "根基"
    },
    {
      "id": 175,
      "quote": "父慈子孝，兄友弟恭，纵做到极处，俱是合当如此。",
      "source": "《菜根谭·家庭篇》",
      "fullText": "父慈子孝，兄友弟恭，纵做到极处，俱是合当如此。天伦之乐，本应如此。",
      "category": "家庭"
    },
    {
      "id": 176,
      "quote": "有妍必有丑为之对，我不夸妍，谁能丑我？",
      "source": "《菜根谭·相对篇》",
      "fullText": "有妍必有丑为之对，我不夸妍，谁能丑我？淡然处之，不受其扰。",
      "category": "相对"
    },
    {
      "id": 177,
      "quote": "有洁必有污为之仇，我不好洁，谁能污我？",
      "source": "《菜根谭·相对篇》",
      "fullText": "有洁必有污为之仇，我不好洁，谁能污我？心无挂碍，自在清净。",
      "category": "相对"
    },
    {
      "id": 178,
      "quote": "炎凉之态，富贵更甚于贫贱。",
      "source": "《菜根谭·人情篇》",
      "fullText": "炎凉之态，富贵更甚于贫贱。富贵场中，人情更薄。",
      "category": "人情"
    },
    {
      "id": 179,
      "quote": "妒忌之心，骨肉尤狠于外人。",
      "source": "《菜根谭·人情篇》",
      "fullText": "妒忌之心，骨肉尤狠于外人。亲人相嫉，更显无情。",
      "category": "人情"
    },
    {
      "id": 180,
      "quote": "功过不容少混，混则人怀惰隳之心。",
      "source": "《菜根谭·管理篇》",
      "fullText": "功过不容少混，混则人怀惰隳之心。赏罚不明，人心涣散。",
      "category": "管理"
    },
    {
      "id": 181,
      "quote": "恩仇不可太明，明则人起携贰之志。",
      "source": "《菜根谭·管理篇》",
      "fullText": "恩仇不可太明，明则人起携贰之志。恩怨太清，人心离散。",
      "category": "管理"
    },
    {
      "id": 182,
      "quote": "爵位不宜太盛，太盛则危。",
      "source": "《菜根谭·中庸篇》",
      "fullText": "爵位不宜太盛，太盛则危。位高权重，危机四伏。",
      "category": "中庸"
    },
    {
      "id": 183,
      "quote": "能事不宜尽毕，尽毕则衰。",
      "source": "《菜根谭·中庸篇》",
      "fullText": "能事不宜尽毕，尽毕则衰。才华尽露，锋芒过露。",
      "category": "中庸"
    },
    {
      "id": 184,
      "quote": "行谊不宜过高，过高则谤兴而毁来。",
      "source": "《菜根谭·中庸篇》",
      "fullText": "行谊不宜过高，过高则谤兴而毁来。品行过高，招致诽谤。",
      "category": "中庸"
    },
    {
      "id": 185,
      "quote": "恶忌阴，善忌阳。",
      "source": "《菜根谭·隐显篇》",
      "fullText": "恶忌阴，善忌阳。善恶分明，各有忌讳。",
      "category": "隐显"
    },
    {
      "id": 186,
      "quote": "德者才之主，才者德之奴。",
      "source": "《菜根谭·德才篇》",
      "fullText": "德者才之主，才者德之奴。德才关系，主次分明。",
      "category": "德才"
    },
    {
      "id": 187,
      "quote": "锄奸杜幸，要放他一条去路。",
      "source": "《菜根谭·宽容篇》",
      "fullText": "锄奸杜幸，要放他一条去路。赶尽杀绝，反受其害。",
      "category": "宽容"
    },
    {
      "id": 188,
      "quote": "当与人同过，不当与人同功。",
      "source": "《菜根谭·共事篇》",
      "fullText": "当与人同过，不当与人同功。共担过失，不争功劳。",
      "category": "共事"
    },
    {
      "id": 189,
      "quote": "可与人共患难，不可与人共安乐。",
      "source": "《菜根谭·共事篇》",
      "fullText": "可与人共患难，不可与人共安乐。患难与共，安乐难享。",
      "category": "共事"
    },
    {
      "id": 190,
      "quote": "饥则附，饱则飏，燠则趋，寒则弃，人情通患也。",
      "source": "《菜根谭·人情篇》",
      "fullText": "饥则附，饱则飏，燠则趋，寒则弃，人情通患也。世态炎凉，古今同慨。",
      "category": "人情"
    },
    {
      "id": 191,
      "quote": "君子宜净拭冷眼，慎勿轻动刚肠。",
      "source": "《菜根谭·冷静篇》",
      "fullText": "君子宜净拭冷眼，慎勿轻动刚肠。冷静观察，理性判断。",
      "category": "冷静"
    },
    {
      "id": 192,
      "quote": "德随量进，量由识长。",
      "source": "《菜根谭·修养篇》",
      "fullText": "德随量进，量由识长。德量识三者，相辅相成。",
      "category": "修养"
    },
    {
      "id": 193,
      "quote": "一苦一乐相磨练，练极而成福者其福始久。",
      "source": "《菜根谭·磨练篇》",
      "fullText": "一苦一乐相磨练，练极而成福者其福始久。苦乐相济，福泽绵长。",
      "category": "磨练"
    },
    {
      "id": 194,
      "quote": "地之秽者多生物，水之清者常无鱼。",
      "source": "《菜根谭·包容篇》",
      "fullText": "地之秽者多生物，水之清者常无鱼。包容万物，方成其大。",
      "category": "包容"
    },
    {
      "id": 195,
      "quote": "泛驾之马可就驰驱，跃冶之金终归型范。",
      "source": "《菜根谭·型范篇》",
      "fullText": "泛驾之马可就驰驱，跃冶之金终归型范。桀骜不驯，终受约束。",
      "category": "型范"
    },
    {
      "id": 196,
      "quote": "人只一念贪私，便销刚为柔。",
      "source": "《菜根谭·贪私篇》",
      "fullText": "人只一念贪私，便销刚为柔。贪念一起，刚气全消。",
      "category": "贪私"
    },
    {
      "id": 197,
      "quote": "塞智为昏，变恩为惨，染洁为污。",
      "source": "《菜根谭·贪私篇》",
      "fullText": "塞智为昏，变恩为惨，染洁为污。贪私之害，无所不至。",
      "category": "贪私"
    },
    {
      "id": 198,
      "quote": "耳目见闻为外贼，情欲意识为内贼。",
      "source": "《菜根谭·内外篇》",
      "fullText": "耳目见闻为外贼，情欲意识为内贼。内外夹攻，防不胜防。",
      "category": "内外"
    },
    {
      "id": 199,
      "quote": "图未就之功，不如保已成之业。",
      "source": "《菜根谭·功业篇》",
      "fullText": "图未就之功，不如保已成之业。务实求稳，着眼现实。",
      "category": "功业"
    },
    {
      "id": 200,
      "quote": "悔既往之失，不如防将来之非。",
      "source": "《菜根谭·功业篇》",
      "fullText": "悔既往之失，不如防将来之非。前事不忘，后事之师。",
      "category": "功业"
    },
    {
      "id": 201,
      "quote": "气象要高旷，而不可疏狂。",
      "source": "《菜根谭·气象篇》",
      "fullText": "气象要高旷，而不可疏狂。气度恢宏，不失规矩。",
      "category": "气象"
    },
    {
      "id": 202,
      "quote": "心思要缜密，而不可琐屑。",
      "source": "《菜根谭·气象篇》",
      "fullText": "心思要缜密，而不可琐屑。思考周密，不钻牛角。",
      "category": "气象"
    },
    {
      "id": 203,
      "quote": "趣味要冲淡，而不可偏枯。",
      "source": "《菜根谭·气象篇》",
      "fullText": "趣味要冲淡，而不可偏枯。兴趣高雅，不失生机。",
      "category": "气象"
    },
    {
      "id": 204,
      "quote": "操守要严明，而不可激烈。",
      "source": "《菜根谭·气象篇》",
      "fullText": "操守要严明，而不可激烈。原则坚定，方法灵活。",
      "category": "气象"
    },
    {
      "id": 205,
      "quote": "风来疏竹，风过而竹不留声。",
      "source": "《菜根谭·心境篇》",
      "fullText": "风来疏竹，风过而竹不留声。来去自如，心无挂碍。",
      "category": "心境"
    },
    {
      "id": 206,
      "quote": "雁渡寒潭，雁去而潭不留影。",
      "source": "《菜根谭·心境篇》",
      "fullText": "雁渡寒潭，雁去而潭不留影。过往不恋，当下不杂。",
      "category": "心境"
    },
    {
      "id": 207,
      "quote": "清能有容，仁能善断。",
      "source": "《菜根谭·懿德篇》",
      "fullText": "清能有容，仁能善断。清正包容，仁爱果断。",
      "category": "懿德"
    },
    {
      "id": 208,
      "quote": "明不伤察，直不过矫。",
      "source": "《菜根谭·懿德篇》",
      "fullText": "明不伤察，直不过矫。明察秋毫，不伤和气。",
      "category": "懿德"
    },
    {
      "id": 209,
      "quote": "贫家净扫地，贫女净梳头。",
      "source": "《菜根谭·风雅篇》",
      "fullText": "贫家净扫地，贫女净梳头。清贫之中，不失风雅。",
      "category": "风雅"
    },
    {
      "id": 210,
      "quote": "学者有段兢业的心思，又要有段潇洒的趣味。",
      "source": "《菜根谭·治学篇》",
      "fullText": "学者有段兢业的心思，又要有段潇洒的趣味。治学严谨，生活潇洒。",
      "category": "治学"
    },
    {
      "id": 211,
      "quote": "真廉无廉名，立名者正所以为贪。",
      "source": "《菜根谭·真伪篇》",
      "fullText": "真廉无廉名，立名者正所以为贪。真廉无名，假廉争名。",
      "category": "真伪"
    },
    {
      "id": 212,
      "quote": "大巧无巧术，用术者乃所以为拙。",
      "source": "《菜根谭·真伪篇》",
      "fullText": "大巧无巧术，用术者乃所以为拙。大巧若拙，小聪明。",
      "category": "真伪"
    },
    {
      "id": 213,
      "quote": "欹器以满覆，扑满以空全。",
      "source": "《菜根谭·盈亏篇》",
      "fullText": "欹器以满覆，扑满以空全。满则倾覆，空则保全。",
      "category": "盈亏"
    },
    {
      "id": 214,
      "quote": "名根未拔者，纵轻千乘甘一瓢，总堕尘情。",
      "source": "《菜根谭·名根篇》",
      "fullText": "名根未拔者，纵轻千乘甘一瓢，总堕尘情。名利之心，难以超脱。",
      "category": "名根"
    },
    {
      "id": 215,
      "quote": "客气未融者，虽泽四海利万世，终为剩技。",
      "source": "《菜根谭·名根篇》",
      "fullText": "客气未融者，虽泽四海利万世，终为剩技。虚浮之气，难成大事。",
      "category": "名根"
    },
    {
      "id": 216,
      "quote": "人心有部真文章，都被残编断简封固了。",
      "source": "《菜根谭·真文章篇》",
      "fullText": "人心有部真文章，都被残编断简封固了。真知在人心，不在书本。",
      "category": "真文章"
    },
    {
      "id": 217,
      "quote": "有部真鼓吹，都被妖歌艳舞湮没了。",
      "source": "《菜根谭·真文章篇》",
      "fullText": "有部真鼓吹，都被妖歌艳舞湮没了。真乐在心中，不在声色。",
      "category": "真文章"
    },
    {
      "id": 218,
      "quote": "天理路上甚宽，稍游心胸中便觉广大宏朗。",
      "source": "《菜根谭·天理篇》",
      "fullText": "天理路上甚宽，稍游心胸中便觉广大宏朗。顺天理，心胸开阔。",
      "category": "天理"
    },
    {
      "id": 219,
      "quote": "人欲路上甚窄，才寄迹眼前俱是荆棘泥涂。",
      "source": "《菜根谭·天理篇》",
      "fullText": "人欲路上甚窄，才寄迹眼前俱是荆棘泥涂。纵人欲，步步艰难。",
      "category": "天理"
    },
    {
      "id": 220,
      "quote": "天地有万古，此身不再得。",
      "source": "《菜根谭·惜时篇》",
      "fullText": "天地有万古，此身不再得。珍惜时光，把握当下。",
      "category": "惜时"
    },
    {
      "id": 221,
      "quote": "人生只百年，此日最易过。",
      "source": "《菜根谭·惜时篇》",
      "fullText": "人生只百年，此日最易过。光阴似箭，珍惜今日。",
      "category": "惜时"
    },
    {
      "id": 222,
      "quote": "宠辱不惊，闲看庭前花开花落。",
      "source": "《菜根谭·闲适篇》",
      "fullText": "宠辱不惊，闲看庭前花开花落。淡然处之，静观其变。",
      "category": "闲适"
    },
    {
      "id": 223,
      "quote": "去留无意，漫随天外云卷云舒。",
      "source": "《菜根谭·闲适篇》",
      "fullText": "去留无意，漫随天外云卷云舒。随遇而安，自在逍遥。",
      "category": "闲适"
    },
    {
      "id": 224,
      "quote": "处世让一步为高，退步即进步的张本。",
      "source": "《菜根谭·处世篇》",
      "fullText": "处世让一步为高，退步即进步的张本。谦让为高，退步进步。",
      "category": "处世"
    },
    {
      "id": 225,
      "quote": "待人宽一分是福，利人实利己的根基。",
      "source": "《菜根谭·处世篇》",
      "fullText": "待人宽一分是福，利人实利己的根基。宽厚待人，福泽自身。",
      "category": "处世"
    },
    {
      "id": 226,
      "quote": "路径窄处留一步，与人行。",
      "source": "《菜根谭·谦让篇》",
      "fullText": "路径窄处留一步，与人行。狭路相逢，退让一步。",
      "category": "谦让"
    },
    {
      "id": 227,
      "quote": "滋味浓的减三分，让人尝。",
      "source": "《菜根谭·谦让篇》",
      "fullText": "滋味浓的减三分，让人尝。美味共享，与人同乐。",
      "category": "谦让"
    },
    {
      "id": 228,
      "quote": "作人无甚高远的事业，摆脱得俗情便入名流。",
      "source": "《菜根谭·作人篇》",
      "fullText": "作人无甚高远的事业，摆脱得俗情便入名流。超脱俗情，便是高人。",
      "category": "作人"
    },
    {
      "id": 229,
      "quote": "为学无甚增益的功夫，减除得物累便臻圣境。",
      "source": "《菜根谭·作人篇》",
      "fullText": "为学无甚增益的功夫，减除得物累便臻圣境。减除物累，方达圣境。",
      "category": "作人"
    },
    {
      "id": 230,
      "quote": "宠利毋居人前，德业毋落人后。",
      "source": "《菜根谭·进退篇》",
      "fullText": "宠利毋居人前，德业毋落人后。谦让名利，勇担德业。",
      "category": "进退"
    },
    {
      "id": 231,
      "quote": "受享毋逾分外，修持毋减分中。",
      "source": "《菜根谭·进退篇》",
      "fullText": "受享毋逾分外，修持毋减分中。知足常乐，精进不懈。",
      "category": "进退"
    },
    {
      "id": 232,
      "quote": "盖世功劳，当不得一个矜字。",
      "source": "《菜根谭·功劳篇》",
      "fullText": "盖世功劳，当不得一个矜字。功劳再大，谦逊为要。",
      "category": "功劳"
    },
    {
      "id": 233,
      "quote": "弥天罪过，当不得一个悔字。",
      "source": "《菜根谭·功劳篇》",
      "fullText": "弥天罪过，当不得一个悔字。罪过再大，悔改为要。",
      "category": "功劳"
    },
    {
      "id": 234,
      "quote": "完名美节，不宜独任，分些与人可以远害全身。",
      "source": "《菜根谭·名节篇》",
      "fullText": "完名美节，不宜独任，分些与人可以远害全身。分享荣誉，保全自身。",
      "category": "名节"
    },
    {
      "id": 235,
      "quote": "辱行污名，不宜全推，引些归己可以韬光养德。",
      "source": "《菜根谭·名节篇》",
      "fullText": "辱行污名，不宜全推，引些归己可以韬光养德。承担过失，修养德行。",
      "category": "名节"
    },
    {
      "id": 236,
      "quote": "事事要留个有余不尽的意思，便造物不能忌我。",
      "source": "《菜根谭·有余篇》",
      "fullText": "事事要留个有余不尽的意思，便造物不能忌我。留有余地，天不妒忌。",
      "category": "有余"
    },
    {
      "id": 237,
      "quote": "攻人之恶毋太严，要思其堪受。",
      "source": "《菜根谭·教化篇》",
      "fullText": "攻人之恶毋太严，要思其堪受。批评有度，顾及感受。",
      "category": "教化"
    },
    {
      "id": 238,
      "quote": "教人以善毋过高，当使其可从。",
      "source": "《菜根谭·教化篇》",
      "fullText": "教人以善毋过高，当使其可从。教诲有方，循序渐进。",
      "category": "教化"
    },
    {
      "id": 239,
      "quote": "粪虫至秽变为蝉，而饮露于秋风。",
      "source": "《菜根谭·转化篇》",
      "fullText": "粪虫至秽变为蝉，而饮露于秋风。卑贱转化，终成高洁。",
      "category": "转化"
    },
    {
      "id": 240,
      "quote": "腐草无光化为萤，而耀彩于夏月。",
      "source": "《菜根谭·转化篇》",
      "fullText": "腐草无光化为萤，而耀彩于夏月。腐朽转化，焕发光彩。",
      "category": "转化"
    },
    {
      "id": 241,
      "quote": "矜高倨傲，无非客气降伏得。",
      "source": "《菜根谭·真心篇》",
      "fullText": "矜高倨傲，无非客气降伏得。傲气虚浮，需要克制。",
      "category": "真心"
    },
    {
      "id": 242,
      "quote": "饱后思味，则浓淡之境都消。",
      "source": "《菜根谭·节制篇》",
      "fullText": "饱后思味，则浓淡之境都消。欲望满足，趣味全无。",
      "category": "节制"
    },
    {
      "id": 243,
      "quote": "色后思淫，则男女之见尽绝。",
      "source": "《菜根谭·节制篇》",
      "fullText": "色后思淫，则男女之见尽绝。情欲过后，心如止水。",
      "category": "节制"
    },
    {
      "id": 244,
      "quote": "人生太闲则别念窃生，太忙则真性不现。",
      "source": "《菜根谭·闲忙篇》",
      "fullText": "人生太闲则别念窃生，太忙则真性不现。闲忙适度，方显真性。",
      "category": "闲忙"
    },
    {
      "id": 245,
      "quote": "君子之心事，天青日白，不可使人不知。",
      "source": "《菜根谭·君子篇》",
      "fullText": "君子之心事，天青日白，不可使人不知。心迹光明，坦荡无私。",
      "category": "君子"
    },
    {
      "id": 246,
      "quote": "君子之才华，玉韫珠藏，不可使人易知。",
      "source": "《菜根谭·君子篇》",
      "fullText": "君子之才华，玉韫珠藏，不可使人易知。才华内敛，深藏不露。",
      "category": "君子"
    },
    {
      "id": 247,
      "quote": "疾风怒雨，禽鸟戚戚。",
      "source": "《菜根谭·气象篇》",
      "fullText": "疾风怒雨，禽鸟戚戚。风雨交加，众生忧惧。",
      "category": "气象"
    },
    {
      "id": 248,
      "quote": "霁日光风，草木欣欣。",
      "source": "《菜根谭·气象篇》",
      "fullText": "霁日光风，草木欣欣。风和日丽，万物欢欣。",
      "category": "气象"
    },
    {
      "id": 249,
      "quote": "恩里由来生害，故快意时须早回头。",
      "source": "《菜根谭·成败篇》",
      "fullText": "恩里由来生害，故快意时须早回头。恩宠过度，反生祸患。",
      "category": "成败"
    },
    {
      "id": 250,
      "quote": "败后或反成功，故拂心处切莫放手。",
      "source": "《菜根谭·成败篇》",
      "fullText": "败后或反成功，故拂心处切莫放手。失败之中，孕育成功。",
      "category": "成败"
    },
    {
      "id": 251,
      "quote": "藜口苋肠者，多冰清玉洁。",
      "source": "《菜根谭·清浊篇》",
      "fullText": "藜口苋肠者，多冰清玉洁。清贫生活，造就高洁。",
      "category": "清浊"
    },
    {
      "id": 252,
      "quote": "衮衣玉食者，甘卑躬屈节。",
      "source": "《菜根谭·清浊篇》",
      "fullText": "衮衣玉食者，甘卑躬屈节。富贵荣华，丧失气节。",
      "category": "清浊"
    },
    {
      "id": 253,
      "quote": "节义之人济以和衷，才不启忿争之路。",
      "source": "《菜根谭·谦和篇》",
      "fullText": "节义之人济以和衷，才不启忿争之路。刚正之中，要有温和。",
      "category": "谦和"
    },
    {
      "id": 254,
      "quote": "功名之士承以谦德，方不开嫉妒之门。",
      "source": "《菜根谭·谦和篇》",
      "fullText": "功名之士承以谦德，方不开嫉妒之门。功成名就，谦逊为要。",
      "category": "谦和"
    },
    {
      "id": 255,
      "quote": "士大夫居官不可竿牍无节，要使人难见，以杜幸端。",
      "source": "《菜根谭·为官篇》",
      "fullText": "士大夫居官不可竿牍无节，要使人难见，以杜幸端。为官清廉，杜绝投机。",
      "category": "为官"
    },
    {
      "id": 256,
      "quote": "居乡不可崖岸太高，要使人易见，以致旧好。",
      "source": "《菜根谭·为官篇》",
      "fullText": "居乡不可崖岸太高，要使人易见，以致旧好。归隐乡里，平易近人。",
      "category": "为官"
    }
  ],
  "totalQuotes": 256
}